odoo/addons/vault/README.rst
odoo/addons/vault/TECHNICAL.rst
odoo/addons/vault/__init__.py
odoo/addons/vault/__manifest__.py
odoo/addons/vault/controllers/__init__.py
odoo/addons/vault/controllers/main.py
odoo/addons/vault/i18n/es.po
odoo/addons/vault/i18n/vault.pot
odoo/addons/vault/models/__init__.py
odoo/addons/vault/models/abstract_vault.py
odoo/addons/vault/models/abstract_vault_field.py
odoo/addons/vault/models/res_config_settings.py
odoo/addons/vault/models/res_users.py
odoo/addons/vault/models/res_users_key.py
odoo/addons/vault/models/vault.py
odoo/addons/vault/models/vault_entry.py
odoo/addons/vault/models/vault_field.py
odoo/addons/vault/models/vault_file.py
odoo/addons/vault/models/vault_inbox.py
odoo/addons/vault/models/vault_inbox_log.py
odoo/addons/vault/models/vault_log.py
odoo/addons/vault/models/vault_right.py
odoo/addons/vault/models/vault_tag.py
odoo/addons/vault/readme/CONTRIBUTORS.rst
odoo/addons/vault/readme/DESCRIPTION.rst
odoo/addons/vault/readme/ROADMAP.rst
odoo/addons/vault/security/ir.model.access.csv
odoo/addons/vault/security/ir_rule.xml
odoo/addons/vault/static/description/icon.png
odoo/addons/vault/static/description/index.html
odoo/addons/vault/static/lib/kdbxweb/kdbxweb.min.js
odoo/addons/vault/static/src/js/user_menu.js
odoo/addons/vault/static/src/js/vault.js
odoo/addons/vault/static/src/js/vault_controller.js
odoo/addons/vault/static/src/js/vault_export.js
odoo/addons/vault/static/src/js/vault_import.js
odoo/addons/vault/static/src/js/vault_inbox.js
odoo/addons/vault/static/src/js/vault_utils.js
odoo/addons/vault/static/src/js/vault_widget.js
odoo/addons/vault/static/src/scss/vault.scss
odoo/addons/vault/static/src/xml/templates.xml
odoo/addons/vault/static/tests/vault_tests.js
odoo/addons/vault/tests/__init__.py
odoo/addons/vault/tests/test_controller.py
odoo/addons/vault/tests/test_inbox.py
odoo/addons/vault/tests/test_log.py
odoo/addons/vault/tests/test_rights.py
odoo/addons/vault/tests/test_user.py
odoo13_addon_vault-13.0.1.4.0.dist-info/METADATA
odoo13_addon_vault-13.0.1.4.0.dist-info/WHEEL
odoo13_addon_vault-13.0.1.4.0.dist-info/top_level.txt
odoo13_addon_vault-13.0.1.4.0.dist-info/RECORD
